pyproject.toml
setup.py
src/some_weird_package/__init__.py
src/some_weird_package.egg-info/PKG-INFO
src/some_weird_package.egg-info/SOURCES.txt
src/some_weird_package.egg-info/dependency_links.txt
src/some_weird_package.egg-info/top_level.txt