Metadata-Version: 2.4
Name: some-weird-package
Version: 0.1.0
Summary: whatever
Author: You
Requires-Python: >=3.9
